{
  "run_id": "20260414T001838Z",
  "collected_at_utc": "2026-04-14T00:18:38+00:00",
  "collector": "rolex_ad",
  "schema_version": "2026-04-13",
  "seed_state_pages": 51,
  "city_pages_discovered": 0,
  "dealer_detail_pages_discovered": 0,
  "aborted_early": true,
  "abort_reason": "Aborted after 5 consecutive seed-page failures with no successful fetches.",
  "fetch_success_count": 0,
  "fetch_failure_count": 5,
  "parsed_record_count": 0,
  "records_with_parser_diagnostics": 0,
  "parser_diagnostic_counts": {},
  "fetch_records": [
    {
      "url": "https://www.rolex.com/en-us/store-locator/unitedstates/alabama",
      "relative_path": "en-us/store-locator/unitedstates/alabama.html",
      "status_code": null,
      "ok": false,
      "error": "URLError: <urlopen error [WinError 10061] No connection could be made because the target machine actively refused it>",
      "content_type": "",
      "bytes_written": 0,
      "sha256_hex": "",
      "fetched_at_utc": "2026-04-14T00:18:38+00:00"
    },
    {
      "url": "https://www.rolex.com/en-us/store-locator/unitedstates/alaska",
      "relative_path": "en-us/store-locator/unitedstates/alaska.html",
      "status_code": null,
      "ok": false,
      "error": "URLError: <urlopen error [WinError 10061] No connection could be made because the target machine actively refused it>",
      "content_type": "",
      "bytes_written": 0,
      "sha256_hex": "",
      "fetched_at_utc": "2026-04-14T00:18:40+00:00"
    },
    {
      "url": "https://www.rolex.com/en-us/store-locator/unitedstates/arizona",
      "relative_path": "en-us/store-locator/unitedstates/arizona.html",
      "status_code": null,
      "ok": false,
      "error": "URLError: <urlopen error [WinError 10061] No connection could be made because the target machine actively refused it>",
      "content_type": "",
      "bytes_written": 0,
      "sha256_hex": "",
      "fetched_at_utc": "2026-04-14T00:18:43+00:00"
    },
    {
      "url": "https://www.rolex.com/en-us/store-locator/unitedstates/arkansas",
      "relative_path": "en-us/store-locator/unitedstates/arkansas.html",
      "status_code": null,
      "ok": false,
      "error": "URLError: <urlopen error [WinError 10061] No connection could be made because the target machine actively refused it>",
      "content_type": "",
      "bytes_written": 0,
      "sha256_hex": "",
      "fetched_at_utc": "2026-04-14T00:18:45+00:00"
    },
    {
      "url": "https://www.rolex.com/en-us/store-locator/unitedstates/california",
      "relative_path": "en-us/store-locator/unitedstates/california.html",
      "status_code": null,
      "ok": false,
      "error": "URLError: <urlopen error [WinError 10061] No connection could be made because the target machine actively refused it>",
      "content_type": "",
      "bytes_written": 0,
      "sha256_hex": "",
      "fetched_at_utc": "2026-04-14T00:18:47+00:00"
    }
  ],
  "state_page_diagnostics": [
    {
      "state_url": "https://www.rolex.com/en-us/store-locator/unitedstates/alabama",
      "ok": false,
      "dealer_links_found": 0,
      "city_links_found": 0,
      "error": "URLError: <urlopen error [WinError 10061] No connection could be made because the target machine actively refused it>"
    },
    {
      "state_url": "https://www.rolex.com/en-us/store-locator/unitedstates/alaska",
      "ok": false,
      "dealer_links_found": 0,
      "city_links_found": 0,
      "error": "URLError: <urlopen error [WinError 10061] No connection could be made because the target machine actively refused it>"
    },
    {
      "state_url": "https://www.rolex.com/en-us/store-locator/unitedstates/arizona",
      "ok": false,
      "dealer_links_found": 0,
      "city_links_found": 0,
      "error": "URLError: <urlopen error [WinError 10061] No connection could be made because the target machine actively refused it>"
    },
    {
      "state_url": "https://www.rolex.com/en-us/store-locator/unitedstates/arkansas",
      "ok": false,
      "dealer_links_found": 0,
      "city_links_found": 0,
      "error": "URLError: <urlopen error [WinError 10061] No connection could be made because the target machine actively refused it>"
    },
    {
      "state_url": "https://www.rolex.com/en-us/store-locator/unitedstates/california",
      "ok": false,
      "dealer_links_found": 0,
      "city_links_found": 0,
      "error": "URLError: <urlopen error [WinError 10061] No connection could be made because the target machine actively refused it>"
    }
  ],
  "interim_snapshot_file": "data/interim/rolex_ad_live_snapshot.csv",
  "source_freshness_utc": "2026-04-14T00:18:38+00:00",
  "source_freshness_date": "2026-04-14"
}